seasons_cal/__init__.py
seasons_cal/__main__.py
seasons_cal/py.typed
seasons_cal-1.0.2.dist-info/METADATA
seasons_cal-1.0.2.dist-info/WHEEL
seasons_cal-1.0.2.dist-info/entry_points.txt
seasons_cal-1.0.2.dist-info/licenses/LICENSE
seasons_cal-1.0.2.dist-info/RECORD
